bits/__init__.py
bits/aws/__init__.py
bits/aws/account.py
bits_aws-1.2.1.dist-info/METADATA
bits_aws-1.2.1.dist-info/WHEEL
bits_aws-1.2.1.dist-info/top_level.txt
bits_aws-1.2.1.dist-info/RECORD
