Metadata-Version: 2.1
Name: bits-aws
Version: 1.2.1
Summary: BITS AWS
Home-page: UNKNOWN
Author: Lukas Karlsson
Author-email: karlsson@broadinstitute.org
License: Apache Software License
Platform: UNKNOWN
Requires-Dist: boto3
